MANIFEST.in
README.rst
setup.py
collective/__init__.py
collective.controlpanel.edit_css.egg-info/PKG-INFO
collective.controlpanel.edit_css.egg-info/SOURCES.txt
collective.controlpanel.edit_css.egg-info/dependency_links.txt
collective.controlpanel.edit_css.egg-info/entry_points.txt
collective.controlpanel.edit_css.egg-info/namespace_packages.txt
collective.controlpanel.edit_css.egg-info/not-zip-safe
collective.controlpanel.edit_css.egg-info/requires.txt
collective.controlpanel.edit_css.egg-info/top_level.txt
collective/controlpanel/__init__.py
collective/controlpanel/edit_css/__init__.py
collective/controlpanel/edit_css/configure.zcml
collective/controlpanel/edit_css/browser/__init__.py
collective/controlpanel/edit_css/browser/configure.zcml
collective/controlpanel/edit_css/browser/edit_css.pt
collective/controlpanel/edit_css/browser/edit_css.py
collective/controlpanel/edit_css/profiles/default/actionicons.xml
collective/controlpanel/edit_css/profiles/default/controlpanel.xml
docs/HISTORY.txt
docs/TODO.txt