Metadata-Version: 1.0
Name: collective.controlpanel.edit-css
Version: 0.4.0
Summary: Use a text area in the Plone control panel to        edit CSS and Javascript.
Home-page: http://collective.github.com/collective.controlpanel.edit_css
Author: Alex Clark
Author-email: aclark@aclark.net
License: ZPL
Keywords: plone theme
Platform: UNKNOWN
Classifier: Framework :: Plone
Classifier: Framework :: Plone :: 3.2
Classifier: Framework :: Plone :: 3.3
Classifier: Framework :: Plone :: 4.0
Classifier: Framework :: Plone :: 4.1
Classifier: Framework :: Plone :: 4.2
Classifier: Framework :: Plone :: 4.3
Classifier: Programming Language :: Python
Classifier: Topic :: Software Development :: Libraries :: Python Modules
